{
"play" : "Play",
	"change_lang" : "Change Language",
	"menu" : "Menu",
	"resume" : "Resume",
	"restart" : "Restart",
	"take_a_shot" : "Hit the ball!",
	"hit_the_enemy" : "Hit the enemy",
	"congratulations" : "Congratulations!",
	"oops_you_failed" : "Ooops, you failed.",
	"great_victory" : "Great Victory!",
	"back" : "Back",
	"language" : "English",
	"flag" : "United_Kingdom.png",
	"en" : "English",
	"ru" : "Русский",
	"de" : "German",
	"es" : "Spanish",
	"fr" : "French",
	"it" : "Italian",
	"pt" : "Portugues",
	"tr" : "Turkish",
    "ua" : "Українська",
	"fullScreen" : "Fullscreen",
	"moreGames" : "More Games",
	"nextGame" : "Next Game",
	"qualification" : "Qualification",
	"groupStage" : "Group stage",
	"play-offRound" : "Play-off round",
	"final" : "Final",
	"scores" : "Scores",
	"chooseYourCountry" : "Choose your country",
    "firstMatch" : "First Match",
    "secondMatch" : "Second Match",
	"firstHalf" : "First Half",
	"secondHalf" : "Second Half",
	"loading" : "Loading"
}