{"Block.0":{"class":"Block","parent":"Scene01","type":"MetalBox","x":599.3865030674847,"y":435.995085995086,"angle":0},"Block.1":{"class":"Block","parent":"Scene01","type":"MetalBox","x":543.1479980964875,"y":378.2555282555283,"angle":0},"Block.2":{"class":"Block","parent":"Scene01","type":"MetalBox","x":489.09853249475896,"y":318.89789423346474,"angle":0},"Block.3":{"class":"Block","parent":"Scene01","type":"MetalBox","x":436.0111123972683,"y":260.3194103194103,"angle":0},"Block.4":{"class":"Block","parent":"Scene01","type":"MetalBox","x":379.9578140474078,"y":202.07072539287302,"angle":0},"Star.0":{"class":"Star","parent":"Scene01","type":"Star","x":658.909853249476,"y":355.8724832214765,"angle":0},"Block.5":{"class":"Block","parent":"Scene01","type":"GlassBox","x":377.9874213836478,"y":146.9798657718121,"angle":0},"Block.6":{"class":"Block","parent":"Scene01","type":"MetalBox","x":383.0188679245283,"y":86.57718120805369,"angle":0},"Block.7":{"class":"Block","parent":"Scene01","type":"MetalBox","x":384.6960167714885,"y":28.691275167785204,"angle":0},"Player.0":{"class":"Player","parent":"Scene01","type":"Player","x":15,"y":383,"balls":3,"scores":[100,150,200],"angle":0}}